eoq3pyecoremdb/__init__.py
eoq3pyecoremdb/pyecoremdb.py
eoq3pyecoremdb/gen/generatepyecoremdb.py
eoq3pyecoremdb/gen/pyecoremdb.init.py
eoq3pyecoremdb/gen/pyecoremdb.old.py
eoq3pyecoremdb/gen/pyecoremdb.prev.py
eoq3pyecoremdb-3.1.0.dist-info/licenses/LICENSE
eoq3pyecoremdb-3.1.0.dist-info/METADATA
eoq3pyecoremdb-3.1.0.dist-info/WHEEL
eoq3pyecoremdb-3.1.0.dist-info/top_level.txt
eoq3pyecoremdb-3.1.0.dist-info/RECORD
