Metadata-Version: 2.4
Name: eoq3pyecoremdb
Version: 3.1.0
Summary: pyecore-based MDB for EOQ3
Author-email: Bjoern Annighoefer <bjoern.annighoefer@ils.uni-stuttgart.de>
Project-URL: Homepage, https://gitlab.com/eoq/py/eoq3pyecoremdb
Project-URL: Issues, https://gitlab.com/eoq/py/eoq3pyecoremdb/-/issues
Classifier: Programming Language :: Python :: 3
Classifier: License :: OSI Approved :: MIT License
Classifier: Operating System :: OS Independent
Requires-Python: >=3.10
License-File: LICENSE
Requires-Dist: eoq3
Requires-Dist: eoq3pyecoreutils
Dynamic: license-file
